{
    "accounts": [
      {
        "id": 1,
        "user": {
          "username": "user1",
          "password": "password1",
          "email": "user1@example.com",
          "details": {
            "first_name": "John",
            "last_name": "Doe",
            "age": 30
          }
        }
      },
      {
        "id": 2,
        "user": {
          "username": "user2",
          "password": "password2",
          "email": "user2@example.com",
          "details": {
            "first_name": "Jane",
            "last_name": "Smith",
            "age": 25
          }
        }
      },
      {
        "id": 3,
        "user": {
          "username": "user3",
          "password": "password3",
          "email": "user3@example.com",
          "details": {
            "first_name": "Alice",
            "last_name": "Johnson",
            "age": 28
          }
        }
      },
      {
        "id": 4,
        "user": {
          "username": "user4",
          "password": "password4",
          "email": "user4@example.com",
          "details": {
            "first_name": "Bob",
            "last_name": "Brown",
            "age": 35
          }
        }
      },
      {
        "id": 5,
        "user": {
          "username": "user5",
          "password": "password5",
          "email": "user5@example.com",
          "details": {
            "first_name": "Carol",
            "last_name": "Davis",
            "age": 22
          }
        }
      }
    ]
  }
  